novaroma_pedro_1234/__init__.py
novaroma_pedro_1234-0.1.0.dist-info/METADATA
novaroma_pedro_1234-0.1.0.dist-info/WHEEL
novaroma_pedro_1234-0.1.0.dist-info/entry_points.txt
novaroma_pedro_1234-0.1.0.dist-info/RECORD
