Metadata-Version: 2.4
Name: novaroma-pedro-1234
Version: 0.1.0
Summary: Add your description here
Author-email: Pedro Augusto <111787739+pepeusilva@users.noreply.github.com>
Requires-Python: >=3.12
Requires-Dist: pandas>=2.2.3
